pyoverinspect/__init__.py
pyoverinspect/overinspect.py
py_overinspect-0.1.0.dist-info/LICENSE
py_overinspect-0.1.0.dist-info/METADATA
py_overinspect-0.1.0.dist-info/WHEEL
py_overinspect-0.1.0.dist-info/RECORD
