Metadata-Version: 2.3
Name: py_overinspect
Version: 0.1.0
Summary: A Python library over standard inspect module
License: MIT
Author: Arnaud Valmary
Requires-Python: >=3.9
Classifier: License :: OSI Approved :: MIT License
Classifier: Programming Language :: Python :: 3
Classifier: Programming Language :: Python :: 3.9
Classifier: Programming Language :: Python :: 3.10
Classifier: Programming Language :: Python :: 3.11
Classifier: Programming Language :: Python :: 3.12
Classifier: Programming Language :: Python :: 3.13
Project-URL: Repository, https://github.com/ArnaudValmary/py_dictflat
